README.md
setup.py
dwzhaopt/__init__.py
dwzhaopt/echo.py
dwzhaopt/useful_1.py
dwzhaopt/useful_2.py
dwzhaopt.egg-info/PKG-INFO
dwzhaopt.egg-info/SOURCES.txt
dwzhaopt.egg-info/dependency_links.txt
dwzhaopt.egg-info/entry_points.txt
dwzhaopt.egg-info/top_level.txt
dwzhaopt/test/__init__.py
dwzhaopt/test/run_all.py
dwzhaopt/test/test.py