Metadata-Version: 1.0
Name: dwzhaopt
Version: 0.0.2
Summary: An demonstration of how to create, test, document and publish to pypi.org.
Home-page: https://github.com/betterzdw/dwzhaopt
Author: dwzhao
Author-email: flybx@foxmail.com
License: MIT License
Keywords: pip test document tutorial
Platform: UNKNOWN
